{"0": "AAFKRSCLK", "1": "ALDPHSGHFV", "2": "ALYGFVPVL", "3": "AVFDRKSDAK", "4": "CINGVCWTV", "5": "CVNGSCFTV", "6": "DATYQRTRALVR", "7": "EAAGIGILTV", "8": "ELAGIGILTV", "9": "FLIYLDVSV", "10": "FLKEKGGL", "11": "GILGFVFTL", "12": "GLCTLVAML", "13": "GTSGSPIVNR", "14": "IPSINVHHY", "15": "IVTDFSVIK", "16": "KASEKIFYV", "17": "KLVALGINAV", "18": "KLYGLDWAEL", "19": "LLWNGPMAV", "20": "NLNCCSVPV", "21": "NLVPMVATV", "22": "NYNYLYRLF", "23": "PKYVKQNTLKLAT", "24": "QYIKWPWYI", "25": "RAKFKQLL", "26": "RLARLALVL", "27": "RPRGEVRFL", "28": "SPRWYFYYL", "29": "TAFTIPSI", "30": "TLWCSPIKV", "31": "TPRVTGGGAM", "32": "VVMSWAPPV", "33": "YLQPRTFLL"}